CephYunweiShouce/README.md
CephYunweiShouce/__init__.py
CephYunweiShouce/__main__.py
CephYunweiShouce/file.epub
CephYunweiShouce/index.html
CephYunweiShouce/css/__init__.py
CephYunweiShouce/css/annotations.css
CephYunweiShouce/css/main.css
CephYunweiShouce/css/normalize.css
CephYunweiShouce/css/popup.css
CephYunweiShouce/font/__init__.py
CephYunweiShouce/font/fontello.eot
CephYunweiShouce/font/fontello.svg
CephYunweiShouce/font/fontello.ttf
CephYunweiShouce/font/fontello.woff
CephYunweiShouce/img/__init__.py
CephYunweiShouce/img/annotator-glyph-sprite.png
CephYunweiShouce/img/annotator-icon-sprite.png
CephYunweiShouce/img/apple-touch-icon.png
CephYunweiShouce/img/cancelfullscreen.png
CephYunweiShouce/img/close.png
CephYunweiShouce/img/fullscreen.png
CephYunweiShouce/img/loader.gif
CephYunweiShouce/img/menu-icon.png
CephYunweiShouce/img/save.png
CephYunweiShouce/img/saved.png
CephYunweiShouce/img/settings-s.png
CephYunweiShouce/img/settings.png
CephYunweiShouce/img/star.png
CephYunweiShouce/js/__init__.py
CephYunweiShouce/js/epub.js
CephYunweiShouce/js/epub.min.js
CephYunweiShouce/js/epub.min.map
CephYunweiShouce/js/hooks.min.js
CephYunweiShouce/js/hooks.min.map
CephYunweiShouce/js/reader.js
CephYunweiShouce/js/reader.js.map
CephYunweiShouce/js/reader.min.js
CephYunweiShouce/js/reader.min.map
CephYunweiShouce/js/hooks/__init__.py
CephYunweiShouce/js/hooks/extensions/__init__.py
CephYunweiShouce/js/hooks/extensions/highlight.js
CephYunweiShouce/js/libs/__init__.py
CephYunweiShouce/js/libs/jquery.min.js
CephYunweiShouce/js/libs/localforage.min.js
CephYunweiShouce/js/libs/screenfull.js
CephYunweiShouce/js/libs/screenfull.min.js
CephYunweiShouce/js/libs/zip.min.js
CephYunweiShouce/js/plugins/__init__.py
CephYunweiShouce/js/plugins/hypothesis.js
CephYunweiShouce/js/plugins/search.js
ceph_yunwei_shouce-2024.3.4.0.dist-info/METADATA
ceph_yunwei_shouce-2024.3.4.0.dist-info/WHEEL
ceph_yunwei_shouce-2024.3.4.0.dist-info/entry_points.txt
ceph_yunwei_shouce-2024.3.4.0.dist-info/top_level.txt
ceph_yunwei_shouce-2024.3.4.0.dist-info/RECORD
